<?xml version="1.0" encoding="utf-8"?>
<Song>
<ID>-1</ID>
<Name>Mata Ashita</Name>
<Author>LNT Guitar</Author>
<Composer>LNT Guitar</Composer>
<Transposes>
<Transpose>
<Name>C Major</Name>
<Keys>
<Key>
<Name>C Major</Name>
<Chords>
<Chord>
<Name>C</Name>
<Apps>
<App>
<Chord>C</Chord>
<AppID>1</AppID>
<Locs>
<Loc>
<Row>2</Row>
<Col>3</Col></Loc>
</Locs>
<Backup>
<Fret>1</Fret>
<Capo>
<Fret>0</Fret>
<Length>0</Length>
</Capo>
<F1>
<Str>2</Str>
<Pos>1</Pos>
<Length>0</Length>
</F1>
<F2>
<Str>4</Str>
<Pos>2</Pos>
<Length>0</Length>
</F2>
<F3>
<Str>5</Str>
<Pos>3</Pos>
<Length>0</Length>
</F3>
<F4>
<Str>0</Str>
<Pos>0</Pos>
<Length>0</Length>
</F4>
<S1>1</S1>
<S2>0</S2>
<S3>1</S3>
<S4>0</S4>
<S5>0</S5>
<S6>-1</S6>
</Backup>
</App>
<App>
<Chord>C</Chord>
<AppID>3</AppID>
<Locs>
<Loc>
<Row>3</Row>
<Col>7</Col></Loc>
</Locs>
<Backup>
<Fret>8</Fret>
<Capo>
<Fret>0</Fret>
<Length>0</Length>
</Capo>
<F1>
<Str>6</Str>
<Pos>1</Pos>
<Length>6</Length>
</F1>
<F2>
<Str>3</Str>
<Pos>2</Pos>
<Length>0</Length>
</F2>
<F3>
<Str>5</Str>
<Pos>3</Pos>
<Length>0</Length>
</F3>
<F4>
<Str>4</Str>
<Pos>3</Pos>
<Length>0</Length>
</F4>
<S1>0</S1>
<S2>0</S2>
<S3>0</S3>
<S4>0</S4>
<S5>0</S5>
<S6>0</S6>
</Backup>
</App>
</Apps>
</Chord>
<Chord>
<Name>G7</Name>
<Apps>
<App>
<Chord>G7</Chord>
<AppID>1</AppID>
<Locs>
<Loc>
<Row>5</Row>
<Col>10</Col></Loc>
</Locs>
<Backup>
<Fret>1</Fret>
<Capo>
<Fret>0</Fret>
<Length>0</Length>
</Capo>
<F1>
<Str>1</Str>
<Pos>1</Pos>
<Length>0</Length>
</F1>
<F2>
<Str>5</Str>
<Pos>2</Pos>
<Length>0</Length>
</F2>
<F3>
<Str>6</Str>
<Pos>3</Pos>
<Length>0</Length>
</F3>
<F4>
<Str>0</Str>
<Pos>0</Pos>
<Length>0</Length>
</F4>
<S1>0</S1>
<S2>1</S2>
<S3>1</S3>
<S4>1</S4>
<S5>0</S5>
<S6>0</S6>
</Backup>
</App>
</Apps>
</Chord>
<Chord>
<Name>Am</Name>
<Apps>
<App>
<Chord>Am</Chord>
<AppID>2</AppID>
<Locs>
<Loc>
<Row>7</Row>
<Col>7</Col></Loc>
<Loc>
<Row>7</Row>
<Col>11</Col></Loc>
</Locs>
<Backup>
<Fret>5</Fret>
<Capo>
<Fret>0</Fret>
<Length>0</Length>
</Capo>
<F1>
<Str>6</Str>
<Pos>1</Pos>
<Length>6</Length>
</F1>
<F2>
<Str>0</Str>
<Pos>0</Pos>
<Length>0</Length>
</F2>
<F3>
<Str>5</Str>
<Pos>3</Pos>
<Length>0</Length>
</F3>
<F4>
<Str>4</Str>
<Pos>3</Pos>
<Length>0</Length>
</F4>
<S1>0</S1>
<S2>0</S2>
<S3>0</S3>
<S4>0</S4>
<S5>0</S5>
<S6>0</S6>
</Backup>
</App>
</Apps>
</Chord>
</Chords>
</Key>
</Keys>
</Transpose>
</Transposes>
<DataRows>
<DataRow>また明日... (Mata Ashita)</DataRow>
<DataRow>+++++</DataRow>
<DataRow>Shizumu yuuhi | ni akaku somaru kaerimichi de</DataRow>
<DataRow>"Ashita mo hareru ne" to warau | anata no hitomi</DataRow>
<DataRow>+++++</DataRow>
<DataRow>Onaji sora wo | miageru no wa kore ga | saigo nante ienai mama</DataRow>
<DataRow>Hohoemi kaeshite nigirishimeta</DataRow>
<DataRow>Sono tenohira no nukumori wa itai | kurai itoshikute atatak | akute</DataRow>
<DataRow>+++++</DataRow>
<DataRow>Mata ashita... anata wo</DataRow>
<DataRow>Dakishimeru yakusoku sae mo dekinai nara</DataRow>
<DataRow>Ima wa tada kagirinai ai de anata no koto wo tsutsumitai</DataRow>
<DataRow>Sayonar a mo iezu ni watashi wo yobu koe ni sae kotaerarenai kedo</DataRow>
<DataRow>Donna ni tooku hanarete mo aishi tsudzuketeru kara</DataRow>
<DataRow>+++++</DataRow>
<DataRow>Nemuru yokogao mitsume nagara mune ga itamu</DataRow>
<DataRow>Anata ni hontou no ai tsutaerareteta no kana?</DataRow>
<DataRow>+++++</DataRow>
<DataRow>Onaji haru wo onaji fuyu wo futari de hitotsu zutsu koete kita kedo</DataRow>
<DataRow>Omoide wa mou fuyasenai no</DataRow>
<DataRow>Soba de yorisou ima sae mo kiseki no you na shiawase de hakana sugite</DataRow>
<DataRow>+++++</DataRow>
<DataRow>Mou nido to... kono te de</DataRow>
<DataRow>Dakishimete ageru koto sae dekinai nara</DataRow>
<DataRow>Anata wo kurushimeru subete kesu koto ga dekita nara</DataRow>
<DataRow>+++++</DataRow>
<DataRow>Sunete naita kao mo hashaideru sono egao mo</DataRow>
<DataRow>Zenbu kakegae no nai hitotsu toshite nakusenai aishite iru</DataRow>
<DataRow>+++++</DataRow>
<DataRow>Mata ashita... anata wo</DataRow>
<DataRow>Dakishimeru yakusoku sae mo dekinai nara</DataRow>
<DataRow>Ima wa tada kagirinai ai de anata no koto wo tsutsumitai</DataRow>
<DataRow>Sayonar a mo iezu ni watashi wo yobu koe ni sae kotaerarenai kedo</DataRow>
<DataRow>Donna ni tooku hanarete mo aishi tsudzuketeru kara</DataRow>
<DataRow>+++++</DataRow>
<DataRow>Mata ashita mo anata wo</DataRow>
</DataRows>
</Song>